composer/__init__.py
composer/analyst.py
composer/cms_post_feed.py
composer/coingecko_feed.py
composer/data_model.py
composer/dsl.py
composer/news_feed.py
composer/notebook_io.py
composer/planner.py
composer/user_profile.py
composer_notebook-0.1.6.dist-info/METADATA
composer_notebook-0.1.6.dist-info/WHEEL
composer_notebook-0.1.6.dist-info/top_level.txt
composer_notebook-0.1.6.dist-info/RECORD
